hestia_dbeaver_connector/__init__.py
hestia_dbeaver_connector/dbeaver_plugin.py
tests/__init__.py
tests/test_dbeaver_plugin.py
hestia_dbeaver_connector-0.1.0.dist-info/METADATA
hestia_dbeaver_connector-0.1.0.dist-info/WHEEL
hestia_dbeaver_connector-0.1.0.dist-info/entry_points.txt
hestia_dbeaver_connector-0.1.0.dist-info/top_level.txt
hestia_dbeaver_connector-0.1.0.dist-info/RECORD
